odoo/addons/account_invoice_report_grouped_by_picking/README.rst
odoo/addons/account_invoice_report_grouped_by_picking/__init__.py
odoo/addons/account_invoice_report_grouped_by_picking/__manifest__.py
odoo/addons/account_invoice_report_grouped_by_picking/i18n/account_invoice_report_grouped_by_picking.pot
odoo/addons/account_invoice_report_grouped_by_picking/i18n/es.po
odoo/addons/account_invoice_report_grouped_by_picking/models/__init__.py
odoo/addons/account_invoice_report_grouped_by_picking/models/account_invoice.py
odoo/addons/account_invoice_report_grouped_by_picking/security/portal_security.xml
odoo/addons/account_invoice_report_grouped_by_picking/static/description/icon.png
odoo/addons/account_invoice_report_grouped_by_picking/tests/__init__.py
odoo/addons/account_invoice_report_grouped_by_picking/tests/test_account_invoice_group_picking.py
odoo/addons/account_invoice_report_grouped_by_picking/views/report_invoice.xml
odoo11_addon_account_invoice_report_grouped_by_picking-11.0.1.4.0.dist-info/METADATA
odoo11_addon_account_invoice_report_grouped_by_picking-11.0.1.4.0.dist-info/RECORD
odoo11_addon_account_invoice_report_grouped_by_picking-11.0.1.4.0.dist-info/WHEEL
odoo11_addon_account_invoice_report_grouped_by_picking-11.0.1.4.0.dist-info/top_level.txt
