Metadata-Version: 2.1
Name: odoo11-addon-account-invoice-report-grouped-by-picking
Version: 11.0.1.4.0
Summary: Print invoice lines grouped by picking
Home-page: https://github.com/OCA/account-invoice-reporting
Author: Tecnativa, Odoo Community Association (OCA)
Author-email: support@odoo-community.org
License: AGPL-3
Platform: UNKNOWN
Classifier: Programming Language :: Python
Classifier: Framework :: Odoo
Classifier: License :: OSI Approved :: GNU Affero General Public License v3
Requires-Python: >=2.7, !=3.0.*, !=3.1.*, !=3.2.*, !=3.3.*, !=3.4.*
Requires-Dist: odoo11-addon-stock-picking-invoice-link
Requires-Dist: odoo (<11.1dev,>=11.0a)
